README.md
setup.py
parselab/__init__.py
parselab/cache.py
parselab/common.py
parselab/db.py
parselab/network.py
parselab/parsing.py
parselab.egg-info/PKG-INFO
parselab.egg-info/SOURCES.txt
parselab.egg-info/dependency_links.txt
parselab.egg-info/requires.txt
parselab.egg-info/top_level.txt