Metadata-Version: 2.1
Name: parselab
Version: 0.1.8
Summary: Parselab helper module
Home-page: http://parselab.ru
Maintainer: Andrei Zhidenkov
Maintainer-email: pensnarik@gmail.com
License: BSD3
Platform: UNKNOWN
